mepost/__init__.py
mepost/client.py
mepost/config.py
mepost/exceptions.py
mepost/helpers.py
mepost_sdk-1.0.5.dist-info/LICENSE
mepost_sdk-1.0.5.dist-info/METADATA
mepost_sdk-1.0.5.dist-info/WHEEL
mepost_sdk-1.0.5.dist-info/top_level.txt
mepost_sdk-1.0.5.dist-info/RECORD
