Metadata-Version: 2.1
Name: mepost-sdk
Version: 1.0.5
Summary: A Python SDK for interacting with the Mepost API.
Home-page: https://github.com/mepost-io/python-sdk
Author: mepost
Author-email: info@mepost.io
License: MIT
Keywords: mepost,email,sdk,api
Classifier: Development Status :: 3 - Alpha
Classifier: Intended Audience :: Developers
Classifier: Topic :: Software Development :: Libraries :: Python Modules
Classifier: License :: OSI Approved :: MIT License
Classifier: Programming Language :: Python :: 3
Classifier: Programming Language :: Python :: 3.6
Classifier: Programming Language :: Python :: 3.7
Classifier: Programming Language :: Python :: 3.8
Classifier: Operating System :: OS Independent
Requires-Python: >=3.6
License-File: LICENSE
Requires-Dist: requests
